LICENSE
binypt_cli/__init__.py
binypt_cli/__main__.py
binypt_cli-1.0.4.dist-info/LICENSE
binypt_cli-1.0.4.dist-info/METADATA
binypt_cli-1.0.4.dist-info/WHEEL
binypt_cli-1.0.4.dist-info/entry_points.txt
binypt_cli-1.0.4.dist-info/RECORD
