Metadata-Version: 2.1
Name: binypt-cli
Version: 1.0.4
Summary: Command line tool for downloading data charts from Binance
Home-page: https://github.com/Tejaromalius/Binypt-cli
License: MIT
Keywords: crypto,binance,cli
Author: ilia tayefi
Author-email: tayefi.ilia@protonmail.com
Requires-Python: >=3.10,<4.0
Classifier: Development Status :: 5 - Production/Stable
Classifier: Intended Audience :: Science/Research
Classifier: License :: OSI Approved :: MIT License
Classifier: Natural Language :: English
Classifier: Operating System :: Unix
Classifier: Programming Language :: Python :: 3
Classifier: Programming Language :: Python :: 3.10
Classifier: Programming Language :: Python :: 3.11
Classifier: Programming Language :: Python :: 3.12
Classifier: Topic :: Utilities
Requires-Dist: argparse (>=1.4.0,<2.0.0)
Requires-Dist: binypt-lib (>=2.3.7,<3.0.0)
Project-URL: Repository, https://github.com/Tejaromalius/Binypt-cli
